sqlobject/__init__.py
sqlobject/__version__.py
sqlobject/boundattributes.py
sqlobject/cache.py
sqlobject/classregistry.py
sqlobject/col.py
sqlobject/compat.py
sqlobject/conftest.py
sqlobject/constraints.py
sqlobject/converters.py
sqlobject/dbconnection.py
sqlobject/dberrors.py
sqlobject/declarative.py
sqlobject/events.py
sqlobject/index.py
sqlobject/joins.py
sqlobject/main.py
sqlobject/sqlbuilder.py
sqlobject/sresults.py
sqlobject/styles.py
sqlobject/views.py
sqlobject/wsgi_middleware.py
sqlobject/firebird/__init__.py
sqlobject/firebird/firebirdconnection.py
sqlobject/include/__init__.py
sqlobject/include/hashcol.py
sqlobject/include/tests/__init__.py
sqlobject/include/tests/test_hashcol.py
sqlobject/inheritance/__init__.py
sqlobject/inheritance/iteration.py
sqlobject/inheritance/tests/__init__.py
sqlobject/inheritance/tests/test_aggregates.py
sqlobject/inheritance/tests/test_asdict.py
sqlobject/inheritance/tests/test_deep_inheritance.py
sqlobject/inheritance/tests/test_destroy_cascade.py
sqlobject/inheritance/tests/test_foreignKey.py
sqlobject/inheritance/tests/test_indexes.py
sqlobject/inheritance/tests/test_inheritance.py
sqlobject/inheritance/tests/test_inheritance_tree.py
sqlobject/manager/__init__.py
sqlobject/manager/command.py
sqlobject/maxdb/__init__.py
sqlobject/maxdb/maxdbconnection.py
sqlobject/maxdb/readme.txt
sqlobject/mssql/__init__.py
sqlobject/mssql/mssqlconnection.py
sqlobject/mysql/__init__.py
sqlobject/mysql/mysqlconnection.py
sqlobject/postgres/__init__.py
sqlobject/postgres/pgconnection.py
sqlobject/sqlite/__init__.py
sqlobject/sqlite/sqliteconnection.py
sqlobject/sybase/__init__.py
sqlobject/sybase/sybaseconnection.py
sqlobject/tests/__init__.py
sqlobject/tests/dbtest.py
sqlobject/tests/test_ForeignKey.py
sqlobject/tests/test_ForeignKey_cascade.py
sqlobject/tests/test_NoneValuedResultItem.py
sqlobject/tests/test_SQLMultipleJoin.py
sqlobject/tests/test_SQLRelatedJoin.py
sqlobject-3.13.1.dist-info/METADATA
sqlobject-3.13.1.dist-info/RECORD
sqlobject-3.13.1.dist-info/WHEEL
sqlobject-3.13.1.dist-info/entry_points.txt
sqlobject-3.13.1.dist-info/top_level.txt
